[{"id": "1597956391658205184", "tweet_text": "@BolsonarotRazao Sim", "tweet_date": "2022-11-30 14:11:07", "geo": "Rio de Janeiro, Brazil", "candidato": "Bolsonaro"}, {"id": "1597956392568360967", "tweet_text": "@VlogdoLisboa O vídeo. https://t.co/FbeBS2QbUl", "tweet_date": "2022-11-30 14:11:07", "geo": "Florianópolis, Brazil", "candidato": "Bolsonaro"}, {"id": "1597956463003324416", "tweet_text": "https://t.co/B7mA5bQKuN https://t.co/ZnDuuvmSU0", "tweet_date": "2022-11-30 14:11:24", "geo": "Sao Paulo, Brazil", "candidato": "Bolsonaro"}, {"id": "1597956533211451393", "tweet_text": "@brom_elisa Elisa, na verdade não queremos ouvir falar mais do ladrão! Apenas quando for capturado e preso pelo Exercito Brasileiro. Mesmo sendo informações negativas, ele terá o que ele quer, estar em noticiários.", "tweet_date": "2022-11-30 14:11:40", "geo": "Barueri, Brasil", "candidato": "Bolsonaro"}, {"id": "1597956562093735937", "tweet_text": "@Oficialluizlima Proibido.....proibido ...proibido.... https://t.co/TgZmrM7zfx", "tweet_date": "2022-11-30 14:11:47", "geo": "Sao Paulo, Brazil", "candidato": "Bolsonaro"}, {"id": "1597956570813722624", "tweet_text": "Essa micheque não tem um pingo de brio na cara, pqp 😖😖😖 https://t.co/mYfLagIszK", "tweet_date": "2022-11-30 14:11:49", "geo": "Rio de Janeiro, Brazil", "candidato": "Bolsonaro"}, {"id": "1597956612056317952", "tweet_text": "@folha Vocês não perdem essa mania de nós subestimar. https://t.co/5wpZea6LkV", "tweet_date": "2022-11-30 14:11:59", "geo": "Rio de Janeiro, Brazil", "candidato": "Bolsonaro"}, {"id": "1597956645216452610", "tweet_text": "@padilhando Não é? Q coisa.....", "tweet_date": "2022-11-30 14:12:07", "geo": "Rio de Janeiro, Brazil", "candidato": "Bolsonaro"}, {"id": "1597956675977502720", "tweet_text": "Tem gente que acreditou e tô rindo disso até agora kkkk https://t.co/PHYk2B5CgA", "tweet_date": "2022-11-30 14:12:14", "geo": "Rio de Janeiro, Brazil", "candidato": "Bolsonaro"}, {"id": "1597956711729754114", "tweet_text": "@UOLNoticias Esse Waldemar ex condenado do Esquema do Mensalão é Bolsonaro está abraçado com ele kkkkkkkkk", "tweet_date": "2022-11-30 14:12:23", "geo": "Luziânia, Brasil", "candidato": "Bolsonaro"}, {"id": "1597956719615053824", "tweet_text": "@PATRlOTAS A felicidade das crianças  kkkkkkk", "tweet_date": "2022-11-30 14:12:25", "geo": "Montes Claros, Brasil", "candidato": "Bolsonaro"}, {"id": "1597956726203875328", "tweet_text": "@FernandoHoliday @AndreJanonesAdv @alexandre Ministros do STF fogem mais uma vez dos debates no Senado !\n#MinistrosDoSTFFugões\n\nhttps://t.co/wFc3vr3ENF", "tweet_date": "2022-11-30 14:12:26", "geo": "Mangaratiba, Brasil", "candidato": "Bolsonaro"}, {"id": "1597956742448435200", "tweet_text": "@folha Popularidade digital , Lul4 é  L4dr40 em todos os cantos  do mundo !!!", "tweet_date": "2022-11-30 14:12:30", "geo": "Piracicaba, Brasil", "candidato": "Bolsonaro"}, {"id": "1597956766490558464", "tweet_text": "Lira chega ao jantar do PL em Brasília sob cobranças justas dos apoiadores de Bolsonaro. https://t.co/4f3nTAHq9z", "tweet_date": "2022-11-30 14:12:36", "geo": "Sao Paulo, Brazil", "candidato": "Bolsonaro"}, {"id": "1597956774711422976", "tweet_text": "Bolsonaro na CADEIA! https://t.co/FliywacV4g", "tweet_date": "2022-11-30 14:12:38", "geo": "Uberlândia, Brasil", "candidato": "Bolsonaro"}, {"id": "1597956789102063617", "tweet_text": "JAIR SAQUEOU O BRASIL https://t.co/M92NFs0ngh", "tweet_date": "2022-11-30 14:12:41", "geo": "João Pessoa, Brazil", "candidato": "Bolsonaro"}, {"id": "1597956790238720001", "tweet_text": "@folha Só se essa popularidade for baseada em seus CRIMES! https://t.co/QuUUXDUPvQ", "tweet_date": "2022-11-30 14:12:42", "geo": "Rio de Janeiro, Brazil", "candidato": "Bolsonaro"}, {"id": "1597956806675820544", "tweet_text": "@SigaGazetaBR Ministros do STF fogem mais uma vez dos debates no Senado !\n#MinistrosDoSTFFugões\n\nhttps://t.co/wFc3vr3ENF", "tweet_date": "2022-11-30 14:12:45", "geo": "Mangaratiba, Brasil", "candidato": "Bolsonaro"}, {"id": "1597956885264891910", "tweet_text": "@folha Popularidade baseada em quem? Em seus crimes? https://t.co/pQoJRqpdLb", "tweet_date": "2022-11-30 14:13:04", "geo": "Rio de Janeiro, Brazil", "candidato": "Bolsonaro"}, {"id": "1597956889341734913", "tweet_text": "@Robertoluzbel61 @jairbolsonaro .\na única coisa que esse Boçal fez nos 4 anos de mandato foi jogar pra sua base, os Gados", "tweet_date": "2022-11-30 14:13:05", "geo": "Fort Worth, TX", "candidato": "Bolsonaro"}, {"id": "1597956917535870977", "tweet_text": "🤣 https://t.co/7Tscw3ZFIV", "tweet_date": "2022-11-30 14:13:12", "geo": "João Pessoa, Brazil", "candidato": "Bolsonaro"}, {"id": "1597956969889169408", "tweet_text": "🐂🐂🐂🐂🐂 Patriota kkkkk https://t.co/v8Onv74GEQ", "tweet_date": "2022-11-30 14:13:24", "geo": "Palmas, Brazil", "candidato": "Bolsonaro"}, {"id": "1597956979150163968", "tweet_text": "@Erica_Bolsonaro @nando_catarino @VolkmerMaria @profpaulamarisa Eu tbm.", "tweet_date": "2022-11-30 14:13:27", "geo": "Fortaleza, Brazil", "candidato": "Bolsonaro"}, {"id": "1597956988084039681", "tweet_text": "@TerraBrasilnot O MELHOR GOVERNO DA HISTÓRIA DO BRASIL 👏🏽👍🏽", "tweet_date": "2022-11-30 14:13:29", "geo": "Paulista, Brasil", "candidato": "Bolsonaro"}, {"id": "1597957018886688769", "tweet_text": "@ElisePistola Bom dia Elise!", "tweet_date": "2022-11-30 14:13:36", "geo": "Sao Paulo, Brazil", "candidato": "Bolsonaro"}, {"id": "1597957070497927171", "tweet_text": "@gleisi Discurso está na ponta da língua. Lá vem outro LÃO .", "tweet_date": "2022-11-30 14:13:48", "geo": "Brazil", "candidato": "Bolsonaro"}, {"id": "1597957207890722817", "tweet_text": "@OGloboPolitica https://t.co/NzCOqQeSPl", "tweet_date": "2022-11-30 14:14:21", "geo": "Porto Alegre, Brazil", "candidato": "Bolsonaro"}, {"id": "1597957272629841922", "tweet_text": "@revistaforum https://t.co/4xYSrsSZhG", "tweet_date": "2022-11-30 14:14:37", "geo": "Porto Alegre, Brazil", "candidato": "Bolsonaro"}, {"id": "1597957302862372864", "tweet_text": "Agr faz o L https://t.co/seDbe02nxh", "tweet_date": "2022-11-30 14:14:44", "geo": "Brasília, Brazil", "candidato": "Bolsonaro"}, {"id": "1597957331844988928", "tweet_text": "@AliciaCastroAR @CFKArgentina @alferdez Y los diputados iniciaron un jury? O también se limitan a comentar? Parece que ni el hijo la acompaña realmente", "tweet_date": "2022-11-30 14:14:51", "geo": "Santa Fe, Argentina", "candidato": "Bolsonaro"}, {"id": "1597957420462280704", "tweet_text": "@joicehasselmann Miss \"pig\", se o Eduardo bolsonaro foi ou não ver o jogo do Brasil isso é problema dele. A pauta não é dele,  a pauta é do povo brasileiro; ou, você não entendeu isso ainda \"traíra\" Coin, coin, coin.", "tweet_date": "2022-11-30 14:15:12", "geo": "Oliveira, Brasil", "candidato": "Bolsonaro"}, {"id": "1597957431417790464", "tweet_text": "@Estadao @dionesterque @EstadaoPolitica Seriam seus nudes?", "tweet_date": "2022-11-30 14:15:14", "geo": "Praia Grande, Brasil", "candidato": "Bolsonaro"}, {"id": "1597957438938173440", "tweet_text": "@alexrribeiro Kakakakkakakakakakakakakakakakakakakakakakakakakakakakak https://t.co/85Qp5OAcka", "tweet_date": "2022-11-30 14:15:16", "geo": "Manaus, Brazil", "candidato": "Bolsonaro"}, {"id": "1597957458248761351", "tweet_text": "@gleisi Necessário mostrar esses problemas, claramente, caso a caso para que as pessoas desinformadas saibam avaliar quem trabalha para o povo!", "tweet_date": "2022-11-30 14:15:21", "geo": "Porto Alegre, Brazil", "candidato": "Bolsonaro"}, {"id": "1597957475361513473", "tweet_text": "@DCM_online Ele deve criar o ministério dos bovinos golpista kkkkkkkk e nomear todos kkkkkkkkkkkkkkkkkkkkkkkkkk", "tweet_date": "2022-11-30 14:15:25", "geo": "Itabuna, Brasil", "candidato": "Bolsonaro"}, {"id": "1597957555250417668", "tweet_text": "@jose_simao https://t.co/8euvtvmWDa", "tweet_date": "2022-11-30 14:15:44", "geo": "Marília, Brazil", "candidato": "Bolsonaro"}, {"id": "1597957585994665984", "tweet_text": "@AliciaCastroAR @CFKArgentina @alferdez Los diputados ya iniciaron algún juicio político? O solo comentan? Parece que ni el hijo se la juega", "tweet_date": "2022-11-30 14:15:51", "geo": "Santa Fe, Argentina", "candidato": "Bolsonaro"}, {"id": "1597957585130618881", "tweet_text": "@gleisi Ou seja, alinhar e aparelhar os cofres públicos para roubar novamente, inclusive com os rombos no teto de gastos! Bem diferente dos anos anteriores, temos uma DIREITA atuante e militares vigilantes e vocês NÃO conseguirão roubar essa nação NOVAMENTE! Que começe o TERCEIRO TURNO!! https://t.co/zpG15KS7QE", "tweet_date": "2022-11-30 14:15:51", "geo": "Araruama, Brasil", "candidato": "Bolsonaro"}, {"id": "1597957593909317634", "tweet_text": "@ThiagoResiste Piada neh ....kkkkkk", "tweet_date": "2022-11-30 14:15:53", "geo": "Brasília, Brazil", "candidato": "Bolsonaro"}, {"id": "1597957883450167296", "tweet_text": "@FernandoHoliday @AndreJanonesAdv @alexandre Realmente o @AndreJanonesAdv atingiu bem no meio tua laia. É só 9 começo. Ano que vem a meta é colocar todos vocês na Cadeia!", "tweet_date": "2022-11-30 14:17:02", "geo": "Porto Alegre, Brazil", "candidato": "Bolsonaro"}, {"id": "1597957971493163009", "tweet_text": "@kimpaim Verdade https://t.co/CMffq4osyp", "tweet_date": "2022-11-30 14:17:23", "geo": "Campos dos Goytacazes, Brasil", "candidato": "Bolsonaro"}, {"id": "1597958016233795585", "tweet_text": "Eu ainda estou impressionado com a cara de pau dessa história do pen drive. Todo dia sai um Bolsonaro de casa e 150 otários. E eles se encontram via redes sociais.", "tweet_date": "2022-11-30 14:17:34", "geo": "Fortaleza, Brazil", "candidato": "Bolsonaro"}, {"id": "1597958079211253760", "tweet_text": "@kalliloliveira_ Só os loucos acreditaram.", "tweet_date": "2022-11-30 14:17:49", "geo": "Campinas, Brasil", "candidato": "Bolsonaro"}, {"id": "1597958133850460161", "tweet_text": "@GuedinhoeFans 1 de janeiro homem assumi", "tweet_date": "2022-11-30 14:18:02", "geo": "Goiânia, Brazil", "candidato": "Bolsonaro"}, {"id": "1597958139416281090", "tweet_text": "@gleisi Não sei porque, nao consigo acreditar em nada que venha do PT sera por isso??👇👇👇 https://t.co/AOYx03rvPi", "tweet_date": "2022-11-30 14:18:03", "geo": "Palhoça, Brasil", "candidato": "Bolsonaro"}, {"id": "1597958212632076289", "tweet_text": "@PastorMalafaia https://t.co/vlsjWWCCXn", "tweet_date": "2022-11-30 14:18:21", "geo": "Campos dos Goytacazes, Brasil", "candidato": "Bolsonaro"}, {"id": "1597958327547629569", "tweet_text": "Não tem como não se emocionar com a garra dos nossos guerreiros para defender nossa pátria !!! 👏👏👏 https://t.co/QG5Zp93U0F", "tweet_date": "2022-11-30 14:18:48", "geo": "Maceió, Brazil", "candidato": "Bolsonaro"}, {"id": "1597958362272239616", "tweet_text": "@CARLOSR86493600 BANANINHA CAÇADO JÁ \nBANANINHA CAÇADO JÁ", "tweet_date": "2022-11-30 14:18:56", "geo": "Porto Alegre, Brazil", "candidato": "Bolsonaro"}, {"id": "1597958429074608128", "tweet_text": "@folha Ñ acredito em nada do que vcs falam. Credibilidade ZERO.😖🤮", "tweet_date": "2022-11-30 14:19:12", "geo": "Rio de Janeiro, Brazil", "candidato": "Bolsonaro"}, {"id": "1597958506241396736", "tweet_text": "Concordo e acho que o povo brasileiro, na sua maioria, agree too. Ele(Bolsonaro) não seria louco de perder um capital político,adquirido nos últimos tempos, incomensuráveis. https://t.co/IVN7h2Kkbc", "tweet_date": "2022-11-30 14:19:31", "geo": "Teresina, Brazil", "candidato": "Bolsonaro"}, {"id": "1597958524382117890", "tweet_text": "@PATRlOTAS https://t.co/d8tAj0KRE1", "tweet_date": "2022-11-30 14:19:35", "geo": "Campos dos Goytacazes, Brasil", "candidato": "Bolsonaro"}, {"id": "1597958547127824384", "tweet_text": "No Dia do Evangélico, apoiadores de Bolsonaro e indígenas dividem o gramado em frente ao Congresso Nacional. Eles questionam o resultado das eleições. https://t.co/k5DZeIcjwf", "tweet_date": "2022-11-30 14:19:40", "geo": "Brasília, Brazil", "candidato": "Bolsonaro"}, {"id": "1597958555545370624", "tweet_text": "@_Ederlicious gloria perez passou roteiro 😳", "tweet_date": "2022-11-30 14:19:42", "geo": "Sao Paulo, Brazil", "candidato": "Bolsonaro"}, {"id": "1597958567050768391", "tweet_text": "@UOLNoticias Vau fazer o quê  ??\n\nVai golpear  ?", "tweet_date": "2022-11-30 14:19:45", "geo": "Brasília, Brazil", "candidato": "Bolsonaro"}, {"id": "1597958584410611712", "tweet_text": "@Eulavomeucarv Hahahaha", "tweet_date": "2022-11-30 14:19:49", "geo": "Sao Paulo, Brazil", "candidato": "Bolsonaro"}, {"id": "1597958592879284226", "tweet_text": "@77_frota Esse cara não presta #bolsonaronacadeia", "tweet_date": "2022-11-30 14:19:51", "geo": "Belo Horizonte, Brazil", "candidato": "Bolsonaro"}, {"id": "1597958663750455296", "tweet_text": "@UOLNoticias https://t.co/jeDYyYRdVL", "tweet_date": "2022-11-30 14:20:08", "geo": "Campos dos Goytacazes, Brasil", "candidato": "Bolsonaro"}, {"id": "1597958742733357057", "tweet_text": "Misericórdia https://t.co/cENBr2Spwh", "tweet_date": "2022-11-30 14:20:27", "geo": "Nova Olinda do Norte, Brasil", "candidato": "Bolsonaro"}, {"id": "1597958788992364551", "tweet_text": "@GuedinhoeFans Cala a boca Malafaia....\nO Pr  sabe o que fazer. Não  precisa ouvir seus berros ...", "tweet_date": "2022-11-30 14:20:38", "geo": "Belo Horizonte, Brazil", "candidato": "Bolsonaro"}, {"id": "1597958815894290434", "tweet_text": "@BolsonarotRazao Sempre", "tweet_date": "2022-11-30 14:20:45", "geo": "Sao Paulo, Brazil", "candidato": "Bolsonaro"}, {"id": "1597958841848958977", "tweet_text": "@gleisi Coitada 🤣🤣🤣", "tweet_date": "2022-11-30 14:20:51", "geo": "Curitiba, Brazil", "candidato": "Bolsonaro"}, {"id": "1597958849117331456", "tweet_text": "Valdemar da Costa Neto -PL\n“Vocês podem ter certeza de que o Bolsonaro vai dar uma resposta pra vocês. Bolsonaro é homem, pode ter certeza de que ele não vai deixar vocês na mão”.\n\n#bolsonaro", "tweet_date": "2022-11-30 14:20:52", "geo": "Caxias do Sul, Brasil", "candidato": "Bolsonaro"}, {"id": "1597958853139628034", "tweet_text": "@gleisi Kkkkk\nE o que vocês fizeram????? HIPÓCRITA.", "tweet_date": "2022-11-30 14:20:53", "geo": "Sao Paulo, Brazil", "candidato": "Bolsonaro"}, {"id": "1597958852431183872", "tweet_text": "@Metropoles @mirelle_ap @carloscarone78 Eu só digo uma coisa, \"todo castigo pra corno é pouco\".", "tweet_date": "2022-11-30 14:20:53", "geo": "Fortaleza, Brazil", "candidato": "Bolsonaro"}, {"id": "1597958871175532544", "tweet_text": "@vanessnnavarro https://t.co/96JhGRy4ay", "tweet_date": "2022-11-30 14:20:58", "geo": "Aracaju, Brazil", "candidato": "Bolsonaro"}, {"id": "1597958893900279808", "tweet_text": "@gleisi Minha resposta! https://t.co/RRrYXammXr", "tweet_date": "2022-11-30 14:21:03", "geo": "Campo Grande, Brazil", "candidato": "Bolsonaro"}, {"id": "1597958920949354496", "tweet_text": "@choquei Alô do pen drive você é um Brincalhão mesmo cara https://t.co/dlmduZARYQ", "tweet_date": "2022-11-30 14:21:10", "geo": "Rio de Janeiro, Brazil", "candidato": "Bolsonaro"}, {"id": "1597958982081339392", "tweet_text": "@PATRlOTAS https://t.co/Uh9pMWR0OD", "tweet_date": "2022-11-30 14:21:24", "geo": "Picos, Brasil", "candidato": "Bolsonaro"}, {"id": "1597959061303332867", "tweet_text": "@SigaGazetaBR Já deixou !", "tweet_date": "2022-11-30 14:21:43", "geo": "Sao Paulo, Brazil", "candidato": "Bolsonaro"}, {"id": "1597959067737391104", "tweet_text": "@MajorMecca Bolsonaro.", "tweet_date": "2022-11-30 14:21:45", "geo": "Rio de Janeiro, Brazil", "candidato": "Bolsonaro"}, {"id": "1597959087077330944", "tweet_text": "@PastorMalafaia Kkkkkkkkkk", "tweet_date": "2022-11-30 14:21:49", "geo": "Sao Paulo, Brazil", "candidato": "Bolsonaro"}, {"id": "1597959124234678272", "tweet_text": "@brasil247 Tik tac", "tweet_date": "2022-11-30 14:21:58", "geo": "Campo Largo, Brasil", "candidato": "Bolsonaro"}, {"id": "1597959138872819712", "tweet_text": "@PastorMalafaia https://t.co/poOadSqMrM", "tweet_date": "2022-11-30 14:22:02", "geo": "Campos dos Goytacazes, Brasil", "candidato": "Bolsonaro"}, {"id": "1597959185144381441", "tweet_text": "@ricardors_22 @MauricioCostaRS Trabalhar não querem", "tweet_date": "2022-11-30 14:22:13", "geo": "Porto Alegre, Brazil", "candidato": "Bolsonaro"}, {"id": "1597959187228946433", "tweet_text": "Meu Deus, esse vídeo! Que vergonha alheia!\n\nÉ nessa que a esquerda perde MUITO ao se apegar demais ao apoio de celebridades. São extremamente despolitizadas e incoerentes.\n\nEssas incoerências revoltam uma parte da população. E com razão\n\n\"A gente só sabe dizer fora Bolsonaro\" https://t.co/2XxfAZr1yw", "tweet_date": "2022-11-30 14:22:13", "geo": "Natal, Brazil", "candidato": "Bolsonaro"}, {"id": "1597959194950660097", "tweet_text": "Não à toa que o Bolsonaro quase foi reeleito https://t.co/XCPoBHd40G", "tweet_date": "2022-11-30 14:22:15", "geo": "Fortaleza, Brazil", "candidato": "Bolsonaro"}, {"id": "1597959195961491456", "tweet_text": "@RicardoAndante @MarizMarcella Ministros do STF fogem mais uma vez dos debates no Senado !\n#MinistrosDoSTFFugões\n\nhttps://t.co/wFc3vqMBLF", "tweet_date": "2022-11-30 14:22:15", "geo": "Mangaratiba, Brasil", "candidato": "Bolsonaro"}, {"id": "1597959216018644992", "tweet_text": "@AndreJanonesAdv O que você tem com isso??? Pq vc não cuida da sua vida e dos seus problemas, que não são poucos? Quer que eu coloque aqui pra todos verem seu vídeo chamando o Lula de ladrão,  dizendo que jamais se envolveria com a máfia do PT???", "tweet_date": "2022-11-30 14:22:20", "geo": "Rio de Janeiro, Brazil", "candidato": "Bolsonaro"}, {"id": "1597959234703880198", "tweet_text": "E o pior tem gente que acredita nas picaretagens https://t.co/iLzEkGTrl9", "tweet_date": "2022-11-30 14:22:24", "geo": "Belo Horizonte, Brazil", "candidato": "Bolsonaro"}, {"id": "1597959241452883969", "tweet_text": "@senadorhumberto Cheque em branco né, sabemos", "tweet_date": "2022-11-30 14:22:26", "geo": "Piumhi, Brasil", "candidato": "Bolsonaro"}, {"id": "1597959299036499968", "tweet_text": "Pra deixar uma coisa bem clara, Bolsonaro acabou faz tempo...pra nunca mais volta...👈🏻", "tweet_date": "2022-11-30 14:22:40", "geo": "Sao Paulo, Brazil", "candidato": "Bolsonaro"}, {"id": "1597959307559342080", "tweet_text": "@77_frota Cê louco, sua noiva.", "tweet_date": "2022-11-30 14:22:42", "geo": "Teresina, Brazil", "candidato": "Bolsonaro"}, {"id": "1597959394297204737", "tweet_text": "@choquei @MarcoRRosa Esse homem tem que ser preso ainda no aeroporto, tramando contra nossa democracia.", "tweet_date": "2022-11-30 14:23:02", "geo": "Brasília, Brazil", "candidato": "Bolsonaro"}, {"id": "1597959433786601472", "tweet_text": "@PastorMalafaia Já faz um bom tempo que o senhor se afastou de suas funções primordiais. Dentre as quais , talvez a mais importante seja falar de Jesus , da palavra.", "tweet_date": "2022-11-30 14:23:12", "geo": "Rio de Janeiro, Brazil", "candidato": "Bolsonaro"}, {"id": "1597959439168176128", "tweet_text": "@Eulavomeucarv Com os gatinhos. https://t.co/SmCiBWeGcQ", "tweet_date": "2022-11-30 14:23:13", "geo": "Lagoa Santa, Brasil", "candidato": "Bolsonaro"}, {"id": "1597959494394269696", "tweet_text": "@jairbolsonaro https://t.co/3Lsm7aeYov", "tweet_date": "2022-11-30 14:23:26", "geo": "Várzea Grande, Brasil", "candidato": "Bolsonaro"}, {"id": "1597959525663133696", "tweet_text": "@GuilhermeBoulos Bandido nessa história é só um.\n#LulaLadraoSeuLugarENaPrisao", "tweet_date": "2022-11-30 14:23:34", "geo": "Bento Gonçalves, Brasil", "candidato": "Bolsonaro"}, {"id": "1597959552359858176", "tweet_text": "e não pode chamar de GENOCIDA https://t.co/is8kccEBBM", "tweet_date": "2022-11-30 14:23:40", "geo": "Curitiba, Brazil", "candidato": "Bolsonaro"}, {"id": "1597959582323970051", "tweet_text": "@brom_elisa @kicaKiquinha @TSEjusbr @STF_oficial juntos com o @LulaOficial irão saquear o Brasil e o @SenadoFederal e @camaradeputados de joelhos.", "tweet_date": "2022-11-30 14:23:47", "geo": "Rio de Janeiro, Brazil", "candidato": "Bolsonaro"}, {"id": "1597959664750456835", "tweet_text": "Queria ir https://t.co/5hUxbDaUJe", "tweet_date": "2022-11-30 14:24:07", "geo": "Salvador, Brazil", "candidato": "Bolsonaro"}, {"id": "1597959724426678272", "tweet_text": "Gente com grana, com acesso s informação, oportunidade de aprender, se aprofundar\n\nMas o trabalho delas no fundo é só esse: fazer propaganda de um estilo de vida de ostentação, vender a ideia de que chegar lá é possível.\n\nJá gostei muito dos meninos, mas essa alienação é demais", "tweet_date": "2022-11-30 14:24:21", "geo": "Natal, Brazil", "candidato": "Bolsonaro"}, {"id": "1597959785688637440", "tweet_text": "@BolsonarotRazao E eu aqui firme! https://t.co/g7fkPqn7CZ", "tweet_date": "2022-11-30 14:24:36", "geo": "Campo Grande, Brazil", "candidato": "Bolsonaro"}, {"id": "1597959863237500928", "tweet_text": "@folha Luladrão nem aparece, popularidade só se for negativa", "tweet_date": "2022-11-30 14:24:54", "geo": "Curitiba, Brazil", "candidato": "Bolsonaro"}, {"id": "1597959891716820992", "tweet_text": "@choquei Ele pode doar a camisa que usou  no dia 28.11 quando estava no hotel, enquanto Danilo mesmo machucado acompanhava a seleção.", "tweet_date": "2022-11-30 14:25:01", "geo": "São Luís, Brazil", "candidato": "Bolsonaro"}, {"id": "1597959951926071296", "tweet_text": "@SergioAJBarrett Ele teve um encontro pessoal com o Sheik Jalin Rabbei! Impressionante. Não deve estar nem sentando ….", "tweet_date": "2022-11-30 14:25:15", "geo": "Sao Paulo, Brazil", "candidato": "Bolsonaro"}, {"id": "1597960094679175168", "tweet_text": "@NikolasFApoio Sim.", "tweet_date": "2022-11-30 14:25:49", "geo": "Rio de Janeiro, Brazil", "candidato": "Bolsonaro"}, {"id": "1597960143085260800", "tweet_text": "@folha Esqueceu que é militar ou nunca foi realmente... \"política não pode entrar dentro do quartel”. “Se entra política pela porta da frente (do quartel), a disciplina e a hierarquia saem pela porta dos fundos”. https://t.co/6QpoNe5eZr", "tweet_date": "2022-11-30 14:26:01", "geo": "Brasília, Brazil", "candidato": "Bolsonaro"}, {"id": "1597960185859174400", "tweet_text": "THESE PHOTOS OF EDUARDO BOLSONARO NENTIROSO EMPLOYEE OF THE BRAZILIAN PEOPLE DEPUTY JAIR'S SON IS JUSTIFYING HE WENT TO THE CUP IN QATAR THESE OLD  LIAR MAY THE HANDS OF GOD BE ON THE HEAD OF THIS TRAITOR TO THE HOMELAND EDUARDO BOLSONARO TRAITOR TO THE BRAZILIAN PEOPLE.  🇧🇷 https://t.co/E8IPJ5x4wG", "tweet_date": "2022-11-30 14:26:11", "geo": "Sao Paulo, Brazil", "candidato": "Bolsonaro"}, {"id": "1597960196546252801", "tweet_text": "@ariellediasbr @BolsonaroSP o mal do povo conservador é a desconfiança sobre a família Bolsonaro. estão se sacrificando pra manter a população livre do atraso do sistema político da corrupção e dos comunistas.Votaram no Bolsonaro mas descontam nele toda a insatisfação do passado. https://t.co/kLjDX0HyYS", "tweet_date": "2022-11-30 14:26:14", "geo": "Rio de Janeiro, Brazil", "candidato": "Bolsonaro"}, {"id": "1597960240107950080", "tweet_text": "@VEJA @radaronline Pois é, o eleitor de Bolsonaro precisa ser estudado pela Nasa: \n👉elegeu os deputados do Bolsonaro \n👉 elegeu os senadores do Bolsonaro \n👉 elegeu os governadores do Bolsonaro \n👉e não  elegeu o presidente Bolsonaro \n🤡🤡🤡🤡🤡🤡", "tweet_date": "2022-11-30 14:26:24", "geo": "Passo Fundo, Brasil", "candidato": "Bolsonaro"}]